<Properties StartupConfiguration="{07509587-19DB-D9A2-D673-3EDEFDF9D3E7}|">
  <MonoDevelop.Ide.Workbench ActiveDocument="Assets/EnableButtonOnDelay.cs">
    <Files>
      <File FileName="Assets/Scripts/MainManager.cs" Line="963" Column="42" />
      <File FileName="Assets/Scripts/Restart.cs" Line="14" Column="5" />
      <File FileName="Assets/EnableButtonOnDelay.cs" Line="13" Column="17" />
    </Files>
  </MonoDevelop.Ide.Workbench>
  <MonoDevelop.Ide.DebuggingService.PinnedWatches />
  <MonoDevelop.Ide.Workspace ActiveConfiguration="Debug" />
  <MonoDevelop.Ide.ItemProperties.Assembly-CSharp PreferredExecutionTarget="Unity.Editor" />
  <MonoDevelop.Ide.DebuggingService.Breakpoints>
    <BreakpointStore />
  </MonoDevelop.Ide.DebuggingService.Breakpoints>
  <MultiItemStartupConfigurations />
</Properties>